powerline_slotmachine/__init__.py
powerline_slotmachine/slotmachine.py
powerline_slotmachine-1.0.0.dist-info/LICENSE
powerline_slotmachine-1.0.0.dist-info/METADATA
powerline_slotmachine-1.0.0.dist-info/WHEEL
powerline_slotmachine-1.0.0.dist-info/top_level.txt
powerline_slotmachine-1.0.0.dist-info/RECORD
