Metadata-Version: 2.1
Name: powerline-slotmachine
Version: 1.0.0
Summary: A toy Powerline segment. This segment shows a slotmachine.
Home-page: https://github.com/mdtrooper/powerline_slotmachine
Author: Miguel de Dios Matias
Author-email: tres.14159@gmail.com
License: GPLv3+
Platform: any
Classifier: Programming Language :: Python :: 3
Classifier: License :: OSI Approved :: GNU General Public License v3 or later (GPLv3+)
Classifier: Operating System :: OS Independent
Classifier: Environment :: Console
Classifier: Topic :: Games/Entertainment
Requires-Python: >=3.7
Requires-Dist: appdirs (>=1.4.3)
